shepherd_mcp/__init__.py
shepherd_mcp/__main__.py
shepherd_mcp/server.py
shepherd_mcp/models/__init__.py
shepherd_mcp/models/aiobs.py
shepherd_mcp/models/langfuse.py
shepherd_mcp/providers/__init__.py
shepherd_mcp/providers/aiobs.py
shepherd_mcp/providers/base.py
shepherd_mcp/providers/langfuse.py
shepherd_mcp-0.0.1.dist-info/METADATA
shepherd_mcp-0.0.1.dist-info/WHEEL
shepherd_mcp-0.0.1.dist-info/entry_points.txt
shepherd_mcp-0.0.1.dist-info/licenses/LICENSE
shepherd_mcp-0.0.1.dist-info/RECORD
