Metadata-Version: 2.4
Name: shepherd-mcp
Version: 0.0.1
Summary: MCP server for Shepherd - Debug your AI agents like you debug your code
Project-URL: Homepage, https://github.com/neuralis/shepherd-mcp
Project-URL: Repository, https://github.com/neuralis/shepherd-mcp
Project-URL: Documentation, https://github.com/neuralis/shepherd-mcp#readme
Author-email: Neuralis <hello@neuralis.ai>
License: MIT
License-File: LICENSE
Keywords: agents,ai,debugging,llm,mcp,observability
Classifier: Development Status :: 4 - Beta
Classifier: Intended Audience :: Developers
Classifier: License :: OSI Approved :: MIT License
Classifier: Programming Language :: Python :: 3
Classifier: Programming Language :: Python :: 3.10
Classifier: Programming Language :: Python :: 3.11
Classifier: Programming Language :: Python :: 3.12
Classifier: Topic :: Software Development :: Debuggers
Requires-Python: >=3.10
Requires-Dist: httpx>=0.27.0
Requires-Dist: mcp>=1.0.0
Requires-Dist: pydantic>=2.0.0
Provides-Extra: dev
Requires-Dist: build>=1.0.0; extra == 'dev'
Requires-Dist: pytest-asyncio>=0.23.0; extra == 'dev'
Requires-Dist: pytest>=8.0.0; extra == 'dev'
Requires-Dist: ruff>=0.5.0; extra == 'dev'
Requires-Dist: twine>=5.0.0; extra == 'dev'
